textin_tester/__init__.py
textin_tester/run_test.py
textin_tester/utils.py
textin_tester/doc/__init__.py
textin_tester/doc/chart.png
textin_tester/doc/table.png
textin_tester/tester/__init__.py
textin_tester/tester/test_function.py
textin_tester/tester/order_evaluation/__init__.py
textin_tester/tester/order_evaluation/order_evaluation.py
textin_tester/tester/table_converter/__init__.py
textin_tester/tester/table_converter/converter.py
textin_tester/tester/table_evaluation/__init__.py
textin_tester/tester/table_evaluation/html_to_metric/__init__.py
textin_tester/tester/table_evaluation/html_to_metric/metric.py
textin_tester/tester/table_evaluation/md_to_metric/__init__.py
textin_tester/tester/table_evaluation/md_to_metric/md_metric.py
textin_tester/tester/text_evaluation/__init__.py
textin_tester/tester/text_evaluation/text_evaluation.py
textin_tester-0.6.0.dist-info/METADATA
textin_tester-0.6.0.dist-info/WHEEL
textin_tester-0.6.0.dist-info/entry_points.txt
textin_tester-0.6.0.dist-info/top_level.txt
textin_tester-0.6.0.dist-info/RECORD
